ferretz/__init__.py
ferretz/ferretz.py
ferretz/template_modules/constants.py.tmpl
ferretz-0.3.dist-info/LICENSE
ferretz-0.3.dist-info/METADATA
ferretz-0.3.dist-info/WHEEL
ferretz-0.3.dist-info/entry_points.txt
ferretz-0.3.dist-info/top_level.txt
ferretz-0.3.dist-info/RECORD
